hyperon_das/__init__.py
hyperon_das/api.py
hyperon_das/das.py
hyperon_das/exceptions.py
hyperon_das/factory.py
hyperon_das/logger.py
hyperon_das/pattern_matcher/__init__.py
hyperon_das/pattern_matcher/constants.py
hyperon_das/pattern_matcher/pattern_matcher.py
ca70c86b0bb3ef4272919ac95fe8809c1edb2-0.1.1.dist-info/METADATA
ca70c86b0bb3ef4272919ac95fe8809c1edb2-0.1.1.dist-info/WHEEL
ca70c86b0bb3ef4272919ac95fe8809c1edb2-0.1.1.dist-info/RECORD
